paideia_contracts/__init__.py
paideia_contracts/contracts/__init__.py
paideia_contracts/contracts/plasma_staking/__init__.py
paideia_contracts/contracts/plasma_staking/ergoscript/latest/plasmaStaking.es
paideia_contracts/contracts/staking/__init__.py
paideia_contracts/contracts/staking/ergoscript/1.0/addStakeProxy.es
paideia_contracts/contracts/staking/ergoscript/1.0/emission.es
paideia_contracts/contracts/staking/ergoscript/1.0/stake.es
paideia_contracts/contracts/staking/ergoscript/1.0/stakePool.es
paideia_contracts/contracts/staking/ergoscript/1.0/stakeProxy.es
paideia_contracts/contracts/staking/ergoscript/1.0/stakeState.es
paideia_contracts/contracts/staking/ergoscript/1.0/stakingIncentive.es
paideia_contracts/contracts/staking/ergoscript/1.0/unstakeProxy.es
paideia_contracts/contracts/staking/ergoscript/1.1/addStakeProxy.es
paideia_contracts/contracts/staking/ergoscript/1.1/emission.es
paideia_contracts/contracts/staking/ergoscript/1.1/stake.es
paideia_contracts/contracts/staking/ergoscript/1.1/stakePool.es
paideia_contracts/contracts/staking/ergoscript/1.1/stakeProxy.es
paideia_contracts/contracts/staking/ergoscript/1.1/stakeState.es
paideia_contracts/contracts/staking/ergoscript/1.1/stakingIncentive.es
paideia_contracts/contracts/staking/ergoscript/1.1/unstakeProxy.es
paideia_contracts/contracts/staking/ergoscript/latest/__init__.py
paideia_contracts/contracts/staking/ergoscript/latest/addStakeProxy.es
paideia_contracts/contracts/staking/ergoscript/latest/emission.es
paideia_contracts/contracts/staking/ergoscript/latest/stake.es
paideia_contracts/contracts/staking/ergoscript/latest/stakePool.es
paideia_contracts/contracts/staking/ergoscript/latest/stakeProxy.es
paideia_contracts/contracts/staking/ergoscript/latest/stakeState.es
paideia_contracts/contracts/staking/ergoscript/latest/stakingIncentive.es
paideia_contracts/contracts/staking/ergoscript/latest/unstakeProxy.es
paideia_contracts-1.1.4.dist-info/LICENSE
paideia_contracts-1.1.4.dist-info/METADATA
paideia_contracts-1.1.4.dist-info/WHEEL
paideia_contracts-1.1.4.dist-info/top_level.txt
paideia_contracts-1.1.4.dist-info/RECORD
