Metadata-Version: 2.1
Name: paideia-contracts
Version: 1.1.4
Summary: ErgoScript and Python wrappers for Paideia
Home-page: https://github.com/ergo-pad/paideia-contracts
Author: Robert Pieter van Leeuwen
Author-email: luivatra@gmail.com
Classifier: Programming Language :: Python :: 3
Classifier: License :: OSI Approved :: MIT License
Classifier: Operating System :: OS Independent
License-File: LICENSE
Requires-Dist: ergo-python-appkit >=0.2.1
Requires-Dist: requests >=2.27.1
